tidystring/__init__.py
tidystring/handlers.py
tidystring/methods.py
tidystring-0.1.0.dist-info/LICENSE
tidystring-0.1.0.dist-info/METADATA
tidystring-0.1.0.dist-info/WHEEL
tidystring-0.1.0.dist-info/RECORD
