Metadata-Version: 2.1
Name: tidystring
Version: 0.1.0
Summary: Tidyverse-style string ops in Python.
Author: Colin Conwell
Author-email: colinconwell@gmail.com
Requires-Python: >=3.9,<4.0
Classifier: Programming Language :: Python :: 3
Classifier: Programming Language :: Python :: 3.9
Classifier: Programming Language :: Python :: 3.10
Classifier: Programming Language :: Python :: 3.11
Requires-Dist: pandas (>=1.2.4)
